CHANGES.rst
LICENSE.txt
MANIFEST.in
README.rst
TODO.txt
setup.py
wesgi/__init__.py
wesgi/tests.py
wesgi.egg-info/PKG-INFO
wesgi.egg-info/SOURCES.txt
wesgi.egg-info/dependency_links.txt
wesgi.egg-info/not-zip-safe
wesgi.egg-info/requires.txt
wesgi.egg-info/top_level.txt