Metadata-Version: 1.1
Name: wesgi
Version: 0.12
Summary: A WSGI middleware which processes ESI directives
Home-page: http://pypi.python.org/pypi/wesgi
Author: Brian Sutherland
Author-email: brian@vanguardistas.net
License: UNKNOWN
Keywords: web middleware wsgi esi
Platform: UNKNOWN
Classifier: Development Status :: 4 - Beta
Classifier: Intended Audience :: Developers
Classifier: Programming Language :: Python
Classifier: License :: OSI Approved :: BSD License
Classifier: Operating System :: OS Independent
Classifier: Topic :: Internet :: WWW/HTTP
Classifier: Topic :: Internet :: WWW/HTTP :: WSGI
Classifier: Topic :: Internet :: WWW/HTTP :: WSGI :: Middleware
Classifier: Programming Language :: Python :: 2.6
Classifier: Programming Language :: Python :: 2.7
Classifier: Programming Language :: Python :: 3.3
Classifier: Programming Language :: Python :: 3.4
Classifier: Programming Language :: Python :: 3.5
